data_sync.v
module data_sync #(
parameter ADDR_WIDTH = 4
)(
input wire clk, 
input wire rst_n,
input wire [ADDR_WIDTH-1:0] in,
output reg [ADDR_WIDTH-1:0] out
);
reg [ADDR_WIDTH-1:0] in_d1;
reg [ADDR_WIDTH-1:0] in_d2;


always @(posedge clk or negedge rst_n) begin
    if(!rst_n) begin
        in_d1 <= 0;
        in_d2 <= 0;
        out <= 0;
    end else begin
        in_d1 <= in;
        in_d2 <= in_d1;
        out <= in_d2;
    end
end

endmodule

b2g_conv.v
module b2g_conv #(
parameter ADDR_WIDTH = 4
)(
input wire [ADDR_WIDTH-1:0] in,
output wire [ADDR_WIDTH-1:0] out
);

assign out = in ^ (in >> 1);

endmodule

async_fifo.v
`include "params.hv"
module async_fifo(
input wire                  wr_clk,
input wire                  rd_clk, 
input wire                  rst_n,
input wire                  wr_enb,
input wire[FIFO_WIDTH-1:0]  wr_data,
input wire                  rd_enb,
output reg [FIFO_WIDTH-1:0] rd_data,
output wire                 full,
output wire                 empty
);

parameter ADDR_WIDTH = FIFO_DEPTH_WIDTH + 1;
parameter FIFO_DEPTH = 1 << FIFO_DEPTH_WIDTH;
reg [ADDR_WIDTH-1:0] wr_addr;
reg [ADDR_WIDTH-1:0] rd_addr;
reg [FIFO_WIDTH-1:0] fifo_mem [FIFO_DEPTH-1:0];
wire [ADDR_WIDTH-1:0] wr_gray;
wire [ADDR_WIDTH-1:0] rd_gray;
wire [ADDR_WIDTH-1:0] sync_wr_gray;
wire [ADDR_WIDTH-1:0] sync_rd_gray;
wire [ADDR_WIDTH-1:0] nxt_rd_addr;
wire [ADDR_WIDTH-1:0] nxt_wr_addr;

assign nxt_wr_addr = wr_addr + {{FIFO_DEPTH_WIDTH{1'd0}},{1'd1}};
always @(posedge wr_clk or negedge rst_n) begin
    if(!rst_n)begin
        wr_addr<={ADDR_WIDTH{1'd0}};
    end else begin
        if(wr_enb & !full) begin
            fifo_mem[wr_addr[FIFO_DEPTH_WIDTH-1:0]]<=wr_data;
            wr_addr<=nxt_wr_addr;
        end
    end
end

assign nxt_rd_addr =rd_addr+{{FIFO_DEPTH_WIDTH{1'd0}},{1'd1}};
always @(posedge rd_clk or negedge rst_n) begin
    if(!rst_n)begin
        rd_addr<={ADDR_WIDTH{1'd0}};
        rd_data<={FIFO_WIDTH{1'd0}};
    end else begin
        if(rd_enb & !empty) begin
            rd_data<=fifo_mem[rd_addr[FIFO_DEPTH_WIDTH-1:0]];
            rd_addr<=nxt_rd_addr;
        end
    end
end

b2g_conv  #(
    .ADDR_WIDTH(ADDR_WIDTH)
) conv1(
    .in(wr_addr),
    .out(wr_gray)
    );
b2g_conv  #(
    .ADDR_WIDTH(ADDR_WIDTH)
) conv2(
    .in(rd_addr),
    .out(rd_gray)
    );
data_sync  #(
    .ADDR_WIDTH(ADDR_WIDTH)
) sync1(
    .clk(wr_clk),
    .rst_n(rst_n),
    .in(rd_gray),
    .out(sync_rd_gray)
    );
data_sync #(
    .ADDR_WIDTH(ADDR_WIDTH)
) sync2 (
    .clk(rd_clk),
    .rst_n(rst_n),
    .in(wr_gray),
    .out(sync_wr_gray)
    );

assign full = (wr_gray == {~sync_rd_gray[ADDR_WIDTH-1:ADDR_WIDTH-2], sync_rd_gray[ADDR_WIDTH-3:0]});
assign empty = (rd_gray == sync_wr_gray) ? 1'b1 : 1'b0;

endmodule

tb_async_fifo.v
`timescale 1ns/1ps
`include "params.hv"
module tb_async_fifo;
reg wr_clk;
reg rd_clk; 
reg rst_n;
reg wr_enb;
reg rd_enb;
reg [FIFO_WIDTH-1:0] wr_data;
wire [FIFO_WIDTH-1:0] rd_data; 
wire full;
wire empty;
reg start_rd;
reg full_seen;
async_fifo fifo(
    .wr_clk         (wr_clk       ),
    .rd_clk         (rd_clk       ),
    .rst_n          (rst_n        ),
    .wr_enb         (wr_enb       ),
    .wr_data        (wr_data      ),
    .rd_enb         (rd_enb       ),
    .rd_data        (rd_data      ),
    .full           (full         ),
    .empty          (empty        )
);

initial begin
    $dumpfile("async_fifo_dump.vcd");
    $dumpvars(0, tb_async_fifo);
    wr_clk = 1'b0;
    rd_clk = 1'b0; 
    start_rd = 1'b0; 
    rst_n = 1'b0;
    wr_enb = 1'b0;
    rd_enb = 1'b0;
    wr_data = {FIFO_WIDTH{1'd0}};
    full_seen = 1'b0;
    #10 rst_n = 1'b1;
    wait(full == 1'b1);
    $display("FIFO full asserted at time %0t", $time);
    #100 start_rd = 1'b1;
    #100000 $finish;
end

always #5 wr_clk = ~wr_clk;
always #10 rd_clk = ~rd_clk;

always @(posedge wr_clk or negedge rst_n) begin
    if(!rst_n) begin
        wr_enb <= 1'd0;
        wr_data <= {FIFO_WIDTH{1'd0}};
    end else begin
        if(full || full_seen) begin
            wr_enb <= 1'd0;
        end else if(!full) begin
            wr_enb <= 1'd1;
            wr_data <= wr_data + {{(FIFO_WIDTH-1){1'd0}},{1'd1}};
        end
    end
end

always@(posedge rd_clk or negedge rst_n) begin
    if(!rst_n) begin
        rd_enb <= 1'd0;
    end else begin
        rd_enb <= start_rd & !empty;
    end
end

always @(posedge wr_clk or negedge rst_n) begin
    if(!rst_n) begin
        full_seen <= 1'b0;
    end else if(full && !full_seen) begin
        full_seen <= 1'b1;
    end
end
endmodule

async_fifo_dump.vcd
$date
	Sun May 10 23:18:10 2026
$end
$version
	Icarus Verilog
$end
$timescale
	1ps
$end
$scope module tb_async_fifo $end
$var wire 8 ! rd_data [7:0] $end
$var wire 1 " full $end
$var wire 1 # empty $end
$var reg 1 $ full_seen $end
$var reg 1 % rd_clk $end
$var reg 1 & rd_enb $end
$var reg 1 ' rst_n $end
$var reg 1 ( start_rd $end
$var reg 1 ) wr_clk $end
$var reg 8 * wr_data [7:0] $end
$var reg 1 + wr_enb $end
$scope module fifo $end
$var wire 1 % rd_clk $end
$var wire 1 & rd_enb $end
$var wire 1 ' rst_n $end
$var wire 1 ) wr_clk $end
$var wire 8 , wr_data [7:0] $end
$var wire 1 + wr_enb $end
$var wire 9 - wr_gray [8:0] $end
$var wire 9 . sync_wr_gray [8:0] $end
$var wire 9 / sync_rd_gray [8:0] $end
$var wire 9 0 rd_gray [8:0] $end
$var wire 9 1 nxt_wr_addr [8:0] $end
$var wire 9 2 nxt_rd_addr [8:0] $end
$var wire 1 " full $end
$var wire 1 # empty $end
$var parameter 33 3 ADDR_WIDTH $end
$var parameter 40 4 FIFO_DEPTH $end
$var reg 9 5 rd_addr [8:0] $end
$var reg 8 6 rd_data [7:0] $end
$var reg 9 7 wr_addr [8:0] $end
$scope module conv1 $end
$var wire 9 8 in [8:0] $end
$var wire 9 9 out [8:0] $end
$var parameter 33 : ADDR_WIDTH $end
$upscope $end
$scope module conv2 $end
$var wire 9 ; in [8:0] $end
$var wire 9 < out [8:0] $end
$var parameter 33 = ADDR_WIDTH $end
$upscope $end
$scope module sync1 $end
$var wire 1 ) clk $end
$var wire 9 > in [8:0] $end
$var wire 1 ' rst_n $end
$var parameter 33 ? ADDR_WIDTH $end
$var reg 9 @ in_d1 [8:0] $end
$var reg 9 A in_d2 [8:0] $end
$var reg 9 B out [8:0] $end
$upscope $end
$scope module sync2 $end
$var wire 1 % clk $end
$var wire 9 C in [8:0] $end
$var wire 1 ' rst_n $end
$var parameter 33 D ADDR_WIDTH $end
$var reg 9 E in_d1 [8:0] $end
$var reg 9 F in_d2 [8:0] $end
$var reg 9 G out [8:0] $end
$upscope $end
$upscope $end
$upscope $end
$enddefinitions $end
$comment Show the parameter values. $end
$dumpall
b1001 D
b1001 ?
b1001 =
b1001 :
b100000000 4
b1001 3
$end
#0
$dumpvars
b0 G
b0 F
b0 E
b0 C
b0 B
b0 A
b0 @
b0 >
b0 <
b0 ;
b0 9
b0 8
b0 7
b0 6
b0 5
b1 2
b1 1
b0 0
b0 /
b0 .
b0 -
b0 ,
0+
b0 *
0)
0(
0'
0&
0%
0$
1#
0"
b0 !
$end
#5000
1)
#10000
0)
1%
1'
#15000
b1 *
b1 ,
1+
1)
#20000
0)
0%
#25000
b1 -
b1 9
b1 C
b10 *
b10 ,
b10 1
b1 7
b1 8
1)
#30000
b1 E
0)
1%
#35000
b11 -
b11 9
b11 C
b11 1
b10 7
b10 8
b11 *
b11 ,
1)
#40000
0)
0%
#45000
b10 -
b10 9
b10 C
b100 *
b100 ,
b100 1
b11 7
b11 8
1)
#50000
b1 F
b10 E
0)
1%
#55000
b110 -
b110 9
b110 C
b101 1
b100 7
b100 8
b101 *
b101 ,
1)
#60000
0)
0%
#65000
b111 -
b111 9
b111 C
b110 *
b110 ,
b110 1
b101 7
b101 8
1)
#70000
0#
b1 .
b1 G
b10 F
b111 E
0)
1%
#75000
b101 -
b101 9
b101 C
b111 1
b110 7
b110 8
b111 *
b111 ,
1)
#80000
0)
0%
#85000
b100 -
b100 9
b100 C
b1000 *
b1000 ,
b1000 1
b111 7
b111 8
1)
#90000
b10 .
b10 G
b111 F
b100 E
0)
1%
#95000
b1100 -
b1100 9
b1100 C
b1001 1
b1000 7
b1000 8
b1001 *
b1001 ,
1)
#100000
0)
0%
#105000
b1101 -
b1101 9
b1101 C
b1010 *
b1010 ,
b1010 1
b1001 7
b1001 8
1)
#110000
b111 .
b111 G
b100 F
b1101 E
0)
1%
#115000
b1111 -
b1111 9
b1111 C
b1011 1
b1010 7
b1010 8
b1011 *
b1011 ,
1)
#120000
0)
0%
#125000
b1110 -
b1110 9
b1110 C
b1100 *
b1100 ,
b1100 1
b1011 7
b1011 8
1)
#130000
b100 .
b100 G
b1101 F
b1110 E
0)
1%
#135000
b1010 -
b1010 9
b1010 C
b1101 1
b1100 7
b1100 8
b1101 *
b1101 ,
1)
#140000
0)
0%
#145000
b1011 -
b1011 9
b1011 C
b1110 *
b1110 ,
b1110 1
b1101 7
b1101 8
1)
#150000
b1101 .
b1101 G
b1110 F
b1011 E
0)
1%
#155000
b1001 -
b1001 9
b1001 C
b1111 1
b1110 7
b1110 8
b1111 *
b1111 ,
1)
#160000
0)
0%
#165000
b1000 -
b1000 9
b1000 C
b10000 *
b10000 ,
b10000 1
b1111 7
b1111 8
1)
#170000
b1110 .
b1110 G
b1011 F
b1000 E
0)
1%
#175000
b11000 -
b11000 9
b11000 C
b10001 1
b10000 7
b10000 8
b10001 *
b10001 ,
1)
#180000
0)
0%
#185000
b11001 -
b11001 9
b11001 C
b10010 *
b10010 ,
b10010 1
b10001 7
b10001 8
1)
#190000
b1011 .
b1011 G
b1000 F
b11001 E
0)
1%
#195000
b11011 -
b11011 9
b11011 C
b10011 1
b10010 7
b10010 8
b10011 *
b10011 ,
1)
#200000
0)
0%
#205000
b11010 -
b11010 9
b11010 C
b10100 *
b10100 ,
b10100 1
b10011 7
b10011 8
1)
#210000
b1000 .
b1000 G
b11001 F
b11010 E
0)
1%
#215000
b11110 -
b11110 9
b11110 C
b10101 1
b10100 7
b10100 8
b10101 *
b10101 ,
1)
#220000
0)
0%
#225000
b11111 -
b11111 9
b11111 C
b10110 *
b10110 ,
b10110 1
b10101 7
b10101 8
1)
#230000
b11001 .
b11001 G
b11010 F
b11111 E
0)
1%
#235000
b11101 -
b11101 9
b11101 C
b10111 1
b10110 7
b10110 8
b10111 *
b10111 ,
1)
#240000
0)
0%
#245000
b11100 -
b11100 9
b11100 C
b11000 *
b11000 ,
b11000 1
b10111 7
b10111 8
1)
#250000
b11010 .
b11010 G
b11111 F
b11100 E
0)
1%
#255000
b10100 -
b10100 9
b10100 C
b11001 1
b11000 7
b11000 8
b11001 *
b11001 ,
1)
#260000
0)
0%
#265000
b10101 -
b10101 9
b10101 C
b11010 *
b11010 ,
b11010 1
b11001 7
b11001 8
1)
#270000
b11111 .
b11111 G
b11100 F
b10101 E
0)
1%
#275000
b10111 -
b10111 9
b10111 C
b11011 1
b11010 7
b11010 8
b11011 *
b11011 ,
1)
#280000
0)
0%
#285000
b10110 -
b10110 9
b10110 C
b11100 *
b11100 ,
b11100 1
b11011 7
b11011 8
1)
#290000
b11100 .
b11100 G
b10101 F
b10110 E
0)
1%
#295000
b10010 -
b10010 9
b10010 C
b11101 1
b11100 7
b11100 8
b11101 *
b11101 ,
1)
#300000
0)
0%
#305000
b10011 -
b10011 9
b10011 C
b11110 *
b11110 ,
b11110 1
b11101 7
b11101 8
1)
#310000
b10101 .
b10101 G
b10110 F
b10011 E
0)
1%
#315000
b10001 -
b10001 9
b10001 C
b11111 1
b11110 7
b11110 8
b11111 *
b11111 ,
1)
#320000
0)
0%
#325000
b10000 -
b10000 9
b10000 C
b100000 *
b100000 ,
b100000 1
b11111 7
b11111 8
1)
#330000
b10110 .
b10110 G
b10011 F
b10000 E
0)
1%
#335000
b110000 -
b110000 9
b110000 C
b100001 1
b100000 7
b100000 8
b100001 *
b100001 ,
1)
#340000
0)
0%
#345000
b110001 -
b110001 9
b110001 C
b100010 *
b100010 ,
b100010 1
b100001 7
b100001 8
1)
#350000
b10011 .
b10011 G
b10000 F
b110001 E
0)
1%
#355000
b110011 -
b110011 9
b110011 C
b100011 1
b100010 7
b100010 8
b100011 *
b100011 ,
1)
#360000
0)
0%
#365000
b110010 -
b110010 9
b110010 C
b100100 *
b100100 ,
b100100 1
b100011 7
b100011 8
1)
#370000
b10000 .
b10000 G
b110001 F
b110010 E
0)
1%
#375000
b110110 -
b110110 9
b110110 C
b100101 1
b100100 7
b100100 8
b100101 *
b100101 ,
1)
#380000
0)
0%
#385000
b110111 -
b110111 9
b110111 C
b100110 *
b100110 ,
b100110 1
b100101 7
b100101 8
1)
#390000
b110001 .
b110001 G
b110010 F
b110111 E
0)
1%
#395000
b110101 -
b110101 9
b110101 C
b100111 1
b100110 7
b100110 8
b100111 *
b100111 ,
1)
#400000
0)
0%
#405000
b110100 -
b110100 9
b110100 C
b101000 *
b101000 ,
b101000 1
b100111 7
b100111 8
1)
#410000
b110010 .
b110010 G
b110111 F
b110100 E
0)
1%
#415000
b111100 -
b111100 9
b111100 C
b101001 1
b101000 7
b101000 8
b101001 *
b101001 ,
1)
#420000
0)
0%
#425000
b111101 -
b111101 9
b111101 C
b101010 *
b101010 ,
b101010 1
b101001 7
b101001 8
1)
#430000
b110111 .
b110111 G
b110100 F
b111101 E
0)
1%
#435000
b111111 -
b111111 9
b111111 C
b101011 1
b101010 7
b101010 8
b101011 *
b101011 ,
1)
#440000
0)
0%
#445000
b111110 -
b111110 9
b111110 C
b101100 *
b101100 ,
b101100 1
b101011 7
b101011 8
1)
#450000
b110100 .
b110100 G
b111101 F
b111110 E
0)
1%
#455000
b111010 -
b111010 9
b111010 C
b101101 1
b101100 7
b101100 8
b101101 *
b101101 ,
1)
#460000
0)
0%
#465000
b111011 -
b111011 9
b111011 C
b101110 *
b101110 ,
b101110 1
b101101 7
b101101 8
1)
#470000
b111101 .
b111101 G
b111110 F
b111011 E
0)
1%
#475000
b111001 -
b111001 9
b111001 C
b101111 1
b101110 7
b101110 8
b101111 *
b101111 ,
1)
#480000
0)
0%
#485000
b111000 -
b111000 9
b111000 C
b110000 *
b110000 ,
b110000 1
b101111 7
b101111 8
1)
#490000
b111110 .
b111110 G
b111011 F
b111000 E
0)
1%
#495000
b101000 -
b101000 9
b101000 C
b110001 1
b110000 7
b110000 8
b110001 *
b110001 ,
1)
#500000
0)
0%
#505000
b101001 -
b101001 9
b101001 C
b110010 *
b110010 ,
b110010 1
b110001 7
b110001 8
1)
#510000
b111011 .
b111011 G
b111000 F
b101001 E
0)
1%
#515000
b101011 -
b101011 9
b101011 C
b110011 1
b110010 7
b110010 8
b110011 *
b110011 ,
1)
#520000
0)
0%
#525000
b101010 -
b101010 9
b101010 C
b110100 *
b110100 ,
b110100 1
b110011 7
b110011 8
1)
#530000
b111000 .
b111000 G
b101001 F
b101010 E
0)
1%
#535000
b101110 -
b101110 9
b101110 C
b110101 1
b110100 7
b110100 8
b110101 *
b110101 ,
1)
#540000
0)
0%
#545000
b101111 -
b101111 9
b101111 C
b110110 *
b110110 ,
b110110 1
b110101 7
b110101 8
1)
#550000
b101001 .
b101001 G
b101010 F
b101111 E
0)
1%
#555000
b101101 -
b101101 9
b101101 C
b110111 1
b110110 7
b110110 8
b110111 *
b110111 ,
1)
#560000
0)
0%
#565000
b101100 -
b101100 9
b101100 C
b111000 *
b111000 ,
b111000 1
b110111 7
b110111 8
1)
#570000
b101010 .
b101010 G
b101111 F
b101100 E
0)
1%
#575000
b100100 -
b100100 9
b100100 C
b111001 1
b111000 7
b111000 8
b111001 *
b111001 ,
1)
#580000
0)
0%
#585000
b100101 -
b100101 9
b100101 C
b111010 *
b111010 ,
b111010 1
b111001 7
b111001 8
1)
#590000
b101111 .
b101111 G
b101100 F
b100101 E
0)
1%
#595000
b100111 -
b100111 9
b100111 C
b111011 1
b111010 7
b111010 8
b111011 *
b111011 ,
1)
#600000
0)
0%
#605000
b100110 -
b100110 9
b100110 C
b111100 *
b111100 ,
b111100 1
b111011 7
b111011 8
1)
#610000
b101100 .
b101100 G
b100101 F
b100110 E
0)
1%
#615000
b100010 -
b100010 9
b100010 C
b111101 1
b111100 7
b111100 8
b111101 *
b111101 ,
1)
#620000
0)
0%
#625000
b100011 -
b100011 9
b100011 C
b111110 *
b111110 ,
b111110 1
b111101 7
b111101 8
1)
#630000
b100101 .
b100101 G
b100110 F
b100011 E
0)
1%
#635000
b100001 -
b100001 9
b100001 C
b111111 1
b111110 7
b111110 8
b111111 *
b111111 ,
1)
#640000
0)
0%
#645000
b100000 -
b100000 9
b100000 C
b1000000 *
b1000000 ,
b1000000 1
b111111 7
b111111 8
1)
#650000
b100110 .
b100110 G
b100011 F
b100000 E
0)
1%
#655000
b1100000 -
b1100000 9
b1100000 C
b1000001 1
b1000000 7
b1000000 8
b1000001 *
b1000001 ,
1)
#660000
0)
0%
#665000
b1100001 -
b1100001 9
b1100001 C
b1000010 *
b1000010 ,
b1000010 1
b1000001 7
b1000001 8
1)
#670000
b100011 .
b100011 G
b100000 F
b1100001 E
0)
1%
#675000
b1100011 -
b1100011 9
b1100011 C
b1000011 1
b1000010 7
b1000010 8
b1000011 *
b1000011 ,
1)
#680000
0)
0%
#685000
b1100010 -
b1100010 9
b1100010 C
b1000100 *
b1000100 ,
b1000100 1
b1000011 7
b1000011 8
1)
#690000
b100000 .
b100000 G
b1100001 F
b1100010 E
0)
1%
#695000
b1100110 -
b1100110 9
b1100110 C
b1000101 1
b1000100 7
b1000100 8
b1000101 *
b1000101 ,
1)
#700000
0)
0%
#705000
b1100111 -
b1100111 9
b1100111 C
b1000110 *
b1000110 ,
b1000110 1
b1000101 7
b1000101 8
1)
#710000
b1100001 .
b1100001 G
b1100010 F
b1100111 E
0)
1%
#715000
b1100101 -
b1100101 9
b1100101 C
b1000111 1
b1000110 7
b1000110 8
b1000111 *
b1000111 ,
1)
#720000
0)
0%
#725000
b1100100 -
b1100100 9
b1100100 C
b1001000 *
b1001000 ,
b1001000 1
b1000111 7
b1000111 8
1)
#730000
b1100010 .
b1100010 G
b1100111 F
b1100100 E
0)
1%
#735000
b1101100 -
b1101100 9
b1101100 C
b1001001 1
b1001000 7
b1001000 8
b1001001 *
b1001001 ,
1)
#740000
0)
0%
#745000
b1101101 -
b1101101 9
b1101101 C
b1001010 *
b1001010 ,
b1001010 1
b1001001 7
b1001001 8
1)
#750000
b1100111 .
b1100111 G
b1100100 F
b1101101 E
0)
1%
#755000
b1101111 -
b1101111 9
b1101111 C
b1001011 1
b1001010 7
b1001010 8
b1001011 *
b1001011 ,
1)
#760000
0)
0%
#765000
b1101110 -
b1101110 9
b1101110 C
b1001100 *
b1001100 ,
b1001100 1
b1001011 7
b1001011 8
1)
#770000
b1100100 .
b1100100 G
b1101101 F
b1101110 E
0)
1%
#775000
b1101010 -
b1101010 9
b1101010 C
b1001101 1
b1001100 7
b1001100 8
b1001101 *
b1001101 ,
1)
#780000
0)
0%
#785000
b1101011 -
b1101011 9
b1101011 C
b1001110 *
b1001110 ,
b1001110 1
b1001101 7
b1001101 8
1)
#790000
b1101101 .
b1101101 G
b1101110 F
b1101011 E
0)
1%
#795000
b1101001 -
b1101001 9
b1101001 C
b1001111 1
b1001110 7
b1001110 8
b1001111 *
b1001111 ,
1)
#800000
0)
0%
#805000
b1101000 -
b1101000 9
b1101000 C
b1010000 *
b1010000 ,
b1010000 1
b1001111 7
b1001111 8
1)
#810000
b1101110 .
b1101110 G
b1101011 F
b1101000 E
0)
1%
#815000
b1111000 -
b1111000 9
b1111000 C
b1010001 1
b1010000 7
b1010000 8
b1010001 *
b1010001 ,
1)
#820000
0)
0%
#825000
b1111001 -
b1111001 9
b1111001 C
b1010010 *
b1010010 ,
b1010010 1
b1010001 7
b1010001 8
1)
#830000
b1101011 .
b1101011 G
b1101000 F
b1111001 E
0)
1%
#835000
b1111011 -
b1111011 9
b1111011 C
b1010011 1
b1010010 7
b1010010 8
b1010011 *
b1010011 ,
1)
#840000
0)
0%
#845000
b1111010 -
b1111010 9
b1111010 C
b1010100 *
b1010100 ,
b1010100 1
b1010011 7
b1010011 8
1)
#850000
b1101000 .
b1101000 G
b1111001 F
b1111010 E
0)
1%
#855000
b1111110 -
b1111110 9
b1111110 C
b1010101 1
b1010100 7
b1010100 8
b1010101 *
b1010101 ,
1)
#860000
0)
0%
#865000
b1111111 -
b1111111 9
b1111111 C
b1010110 *
b1010110 ,
b1010110 1
b1010101 7
b1010101 8
1)
#870000
b1111001 .
b1111001 G
b1111010 F
b1111111 E
0)
1%
#875000
b1111101 -
b1111101 9
b1111101 C
b1010111 1
b1010110 7
b1010110 8
b1010111 *
b1010111 ,
1)
#880000
0)
0%
#885000
b1111100 -
b1111100 9
b1111100 C
b1011000 *
b1011000 ,
b1011000 1
b1010111 7
b1010111 8
1)
#890000
b1111010 .
b1111010 G
b1111111 F
b1111100 E
0)
1%
#895000
b1110100 -
b1110100 9
b1110100 C
b1011001 1
b1011000 7
b1011000 8
b1011001 *
b1011001 ,
1)
#900000
0)
0%
#905000
b1110101 -
b1110101 9
b1110101 C
b1011010 *
b1011010 ,
b1011010 1
b1011001 7
b1011001 8
1)
#910000
b1111111 .
b1111111 G
b1111100 F
b1110101 E
0)
1%
#915000
b1110111 -
b1110111 9
b1110111 C
b1011011 1
b1011010 7
b1011010 8
b1011011 *
b1011011 ,
1)
#920000
0)
0%
#925000
b1110110 -
b1110110 9
b1110110 C
b1011100 *
b1011100 ,
b1011100 1
b1011011 7
b1011011 8
1)
#930000
b1111100 .
b1111100 G
b1110101 F
b1110110 E
0)
1%
#935000
b1110010 -
b1110010 9
b1110010 C
b1011101 1
b1011100 7
b1011100 8
b1011101 *
b1011101 ,
1)
#940000
0)
0%
#945000
b1110011 -
b1110011 9
b1110011 C
b1011110 *
b1011110 ,
b1011110 1
b1011101 7
b1011101 8
1)
#950000
b1110101 .
b1110101 G
b1110110 F
b1110011 E
0)
1%
#955000
b1110001 -
b1110001 9
b1110001 C
b1011111 1
b1011110 7
b1011110 8
b1011111 *
b1011111 ,
1)
#960000
0)
0%
#965000
b1110000 -
b1110000 9
b1110000 C
b1100000 *
b1100000 ,
b1100000 1
b1011111 7
b1011111 8
1)
#970000
b1110110 .
b1110110 G
b1110011 F
b1110000 E
0)
1%
#975000
b1010000 -
b1010000 9
b1010000 C
b1100001 1
b1100000 7
b1100000 8
b1100001 *
b1100001 ,
1)
#980000
0)
0%
#985000
b1010001 -
b1010001 9
b1010001 C
b1100010 *
b1100010 ,
b1100010 1
b1100001 7
b1100001 8
1)
#990000
b1110011 .
b1110011 G
b1110000 F
b1010001 E
0)
1%
#995000
b1010011 -
b1010011 9
b1010011 C
b1100011 1
b1100010 7
b1100010 8
b1100011 *
b1100011 ,
1)
#1000000
0)
0%
#1005000
b1010010 -
b1010010 9
b1010010 C
b1100100 *
b1100100 ,
b1100100 1
b1100011 7
b1100011 8
1)
#1010000
b1110000 .
b1110000 G
b1010001 F
b1010010 E
0)
1%
#1015000
b1010110 -
b1010110 9
b1010110 C
b1100101 1
b1100100 7
b1100100 8
b1100101 *
b1100101 ,
1)
#1020000
0)
0%
#1025000
b1010111 -
b1010111 9
b1010111 C
b1100110 *
b1100110 ,
b1100110 1
b1100101 7
b1100101 8
1)
#1030000
b1010001 .
b1010001 G
b1010010 F
b1010111 E
0)
1%
#1035000
b1010101 -
b1010101 9
b1010101 C
b1100111 1
b1100110 7
b1100110 8
b1100111 *
b1100111 ,
1)
#1040000
0)
0%
#1045000
b1010100 -
b1010100 9
b1010100 C
b1101000 *
b1101000 ,
b1101000 1
b1100111 7
b1100111 8
1)
#1050000
b1010010 .
b1010010 G
b1010111 F
b1010100 E
0)
1%
#1055000
b1011100 -
b1011100 9
b1011100 C
b1101001 1
b1101000 7
b1101000 8
b1101001 *
b1101001 ,
1)
#1060000
0)
0%
#1065000
b1011101 -
b1011101 9
b1011101 C
b1101010 *
b1101010 ,
b1101010 1
b1101001 7
b1101001 8
1)
#1070000
b1010111 .
b1010111 G
b1010100 F
b1011101 E
0)
1%
#1075000
b1011111 -
b1011111 9
b1011111 C
b1101011 1
b1101010 7
b1101010 8
b1101011 *
b1101011 ,
1)
#1080000
0)
0%
#1085000
b1011110 -
b1011110 9
b1011110 C
b1101100 *
b1101100 ,
b1101100 1
b1101011 7
b1101011 8
1)
#1090000
b1010100 .
b1010100 G
b1011101 F
b1011110 E
0)
1%
#1095000
b1011010 -
b1011010 9
b1011010 C
b1101101 1
b1101100 7
b1101100 8
b1101101 *
b1101101 ,
1)
#1100000
0)
0%
#1105000
b1011011 -
b1011011 9
b1011011 C
b1101110 *
b1101110 ,
b1101110 1
b1101101 7
b1101101 8
1)
#1110000
b1011101 .
b1011101 G
b1011110 F
b1011011 E
0)
1%
#1115000
b1011001 -
b1011001 9
b1011001 C
b1101111 1
b1101110 7
b1101110 8
b1101111 *
b1101111 ,
1)
#1120000
0)
0%
#1125000
b1011000 -
b1011000 9
b1011000 C
b1110000 *
b1110000 ,
b1110000 1
b1101111 7
b1101111 8
1)
#1130000
b1011110 .
b1011110 G
b1011011 F
b1011000 E
0)
1%
#1135000
b1001000 -
b1001000 9
b1001000 C
b1110001 1
b1110000 7
b1110000 8
b1110001 *
b1110001 ,
1)
#1140000
0)
0%
#1145000
b1001001 -
b1001001 9
b1001001 C
b1110010 *
b1110010 ,
b1110010 1
b1110001 7
b1110001 8
1)
#1150000
b1011011 .
b1011011 G
b1011000 F
b1001001 E
0)
1%
#1155000
b1001011 -
b1001011 9
b1001011 C
b1110011 1
b1110010 7
b1110010 8
b1110011 *
b1110011 ,
1)
#1160000
0)
0%
#1165000
b1001010 -
b1001010 9
b1001010 C
b1110100 *
b1110100 ,
b1110100 1
b1110011 7
b1110011 8
1)
#1170000
b1011000 .
b1011000 G
b1001001 F
b1001010 E
0)
1%
#1175000
b1001110 -
b1001110 9
b1001110 C
b1110101 1
b1110100 7
b1110100 8
b1110101 *
b1110101 ,
1)
#1180000
0)
0%
#1185000
b1001111 -
b1001111 9
b1001111 C
b1110110 *
b1110110 ,
b1110110 1
b1110101 7
b1110101 8
1)
#1190000
b1001001 .
b1001001 G
b1001010 F
b1001111 E
0)
1%
#1195000
b1001101 -
b1001101 9
b1001101 C
b1110111 1
b1110110 7
b1110110 8
b1110111 *
b1110111 ,
1)
#1200000
0)
0%
#1205000
b1001100 -
b1001100 9
b1001100 C
b1111000 *
b1111000 ,
b1111000 1
b1110111 7
b1110111 8
1)
#1210000
b1001010 .
b1001010 G
b1001111 F
b1001100 E
0)
1%
#1215000
b1000100 -
b1000100 9
b1000100 C
b1111001 1
b1111000 7
b1111000 8
b1111001 *
b1111001 ,
1)
#1220000
0)
0%
#1225000
b1000101 -
b1000101 9
b1000101 C
b1111010 *
b1111010 ,
b1111010 1
b1111001 7
b1111001 8
1)
#1230000
b1001111 .
b1001111 G
b1001100 F
b1000101 E
0)
1%
#1235000
b1000111 -
b1000111 9
b1000111 C
b1111011 1
b1111010 7
b1111010 8
b1111011 *
b1111011 ,
1)
#1240000
0)
0%
#1245000
b1000110 -
b1000110 9
b1000110 C
b1111100 *
b1111100 ,
b1111100 1
b1111011 7
b1111011 8
1)
#1250000
b1001100 .
b1001100 G
b1000101 F
b1000110 E
0)
1%
#1255000
b1000010 -
b1000010 9
b1000010 C
b1111101 1
b1111100 7
b1111100 8
b1111101 *
b1111101 ,
1)
#1260000
0)
0%
#1265000
b1000011 -
b1000011 9
b1000011 C
b1111110 *
b1111110 ,
b1111110 1
b1111101 7
b1111101 8
1)
#1270000
b1000101 .
b1000101 G
b1000110 F
b1000011 E
0)
1%
#1275000
b1000001 -
b1000001 9
b1000001 C
b1111111 1
b1111110 7
b1111110 8
b1111111 *
b1111111 ,
1)
#1280000
0)
0%
#1285000
b1000000 -
b1000000 9
b1000000 C
b10000000 *
b10000000 ,
b10000000 1
b1111111 7
b1111111 8
1)
#1290000
b1000110 .
b1000110 G
b1000011 F
b1000000 E
0)
1%
#1295000
b11000000 -
b11000000 9
b11000000 C
b10000001 1
b10000000 7
b10000000 8
b10000001 *
b10000001 ,
1)
#1300000
0)
0%
#1305000
b11000001 -
b11000001 9
b11000001 C
b10000010 *
b10000010 ,
b10000010 1
b10000001 7
b10000001 8
1)
#1310000
b1000011 .
b1000011 G
b1000000 F
b11000001 E
0)
1%
#1315000
b11000011 -
b11000011 9
b11000011 C
b10000011 1
b10000010 7
b10000010 8
b10000011 *
b10000011 ,
1)
#1320000
0)
0%
#1325000
b11000010 -
b11000010 9
b11000010 C
b10000100 *
b10000100 ,
b10000100 1
b10000011 7
b10000011 8
1)
#1330000
b1000000 .
b1000000 G
b11000001 F
b11000010 E
0)
1%
