data_sync.v
module data_sync #(
parameter ADDR_WIDTH = 4
)(
input wire clk, 
input wire rst_n,
input wire [ADDR_WIDTH-1:0] in,
output reg [ADDR_WIDTH-1:0] out
);
reg [ADDR_WIDTH-1:0] in_d1;
reg [ADDR_WIDTH-1:0] in_d2;


always @(posedge clk or negedge rst_n) begin
    if(!rst_n) begin
        in_d1 <= 0;
        in_d2 <= 0;
        out <= 0;
    end else begin
        in_d1 <= in;
        in_d2 <= in_d1;
        out <= in_d2;
    end
end

endmodule

b2g_conv.v
module b2g_conv #(
parameter ADDR_WIDTH = 4
)(
input wire [ADDR_WIDTH-1:0] in,
output wire [ADDR_WIDTH-1:0] out
);

assign out = in ^ (in >> 1);

endmodule

async_fifo.v
`include "params.hv"
module async_fifo(
input wire                  wr_clk,
input wire                  rd_clk, 
input wire                  rst_n,
input wire                  wr_enb,
input wire[FIFO_WIDTH-1:0]  wr_data,
input wire                  rd_enb,
output reg [FIFO_WIDTH-1:0] rd_data,
output wire                 full,
output wire                 empty
);

parameter ADDR_WIDTH = FIFO_DEPTH_WIDTH + 1;
parameter FIFO_DEPTH = 1 << FIFO_DEPTH_WIDTH;
reg [ADDR_WIDTH-1:0] wr_addr;
reg [ADDR_WIDTH-1:0] rd_addr;
reg [FIFO_WIDTH-1:0] fifo_mem [FIFO_DEPTH-1:0];
wire [ADDR_WIDTH-1:0] g_wr_addr;
wire [ADDR_WIDTH-1:0] g_rd_addr;
wire [ADDR_WIDTH-1:0] sync_wr_addr;
wire [ADDR_WIDTH-1:0] sync_rd_addr;
wire [ADDR_WIDTH-1:0] nxt_rd_addr;
wire [ADDR_WIDTH-1:0] nxt_wr_addr;

assign nxt_wr_addr = wr_addr + {{FIFO_DEPTH_WIDTH{1'd0}},{1'd1}};
always @(posedge wr_clk or negedge rst_n) begin
    if(!rst_n)begin
        wr_addr<={ADDR_WIDTH{1'd0}};
    end else begin
        if(wr_enb & !full) begin
            fifo_mem[wr_addr[FIFO_DEPTH_WIDTH-1:0]]<=wr_data;
            wr_addr<=nxt_wr_addr;
        end
    end
end

assign nxt_rd_addr =rd_addr+{{FIFO_DEPTH_WIDTH{1'd0}},{1'd1}};
always @(posedge rd_clk or negedge rst_n) begin
    if(!rst_n)begin
        rd_addr<={ADDR_WIDTH{1'd0}};
        rd_data<={FIFO_WIDTH{1'd0}};
    end else begin
        if(rd_enb & !empty) begin
            rd_data<=fifo_mem[rd_addr[FIFO_DEPTH_WIDTH-1:0]];
            rd_addr<=nxt_rd_addr;
        end
    end
end

b2g_conv  #(
    .ADDR_WIDTH(ADDR_WIDTH)
) conv1(
    .in({nxt_wr_addr}),
    .out({g_wr_addr})
    );
b2g_conv  #(
    .ADDR_WIDTH(ADDR_WIDTH)
) conv2(
    .in({nxt_rd_addr}),
    .out({g_rd_addr})
    );

data_sync  #(
    .ADDR_WIDTH(ADDR_WIDTH)
) sync1(
    .clk(wr_clk),
    .rst_n(rst_n),
    .in({g_rd_addr}),
    .out({sync_rd_addr})
    );
data_sync #(
    .ADDR_WIDTH(ADDR_WIDTH)
) sync2 (
    .clk(rd_clk),
    .rst_n(rst_n),
    .in({g_wr_addr}),
    .out({sync_wr_addr})
    );

assign full = (g_wr_addr == {~sync_rd_addr[ADDR_WIDTH-1:ADDR_WIDTH-2], sync_rd_addr[ADDR_WIDTH-3:0]});
assign empty = (g_rd_addr == sync_wr_addr) ? 1'b1 : 1'b0;

endmodule

tb_async_fifo.v
`timescale 1ns/1ps
`include "params.hv"
module tb_async_fifo;
reg wr_clk;
reg rd_clk; 
reg rst_n;
reg wr_enb;
reg rd_enb;
reg [FIFO_WIDTH-1:0] wr_data;
wire [FIFO_WIDTH-1:0] rd_data; 
wire full;
wire empty;
reg start_rd;
async_fifo fifo(
    .wr_clk         (wr_clk       ),
    .rd_clk         (rd_clk       ),
    .rst_n          (rst_n        ),
    .wr_enb         (wr_enb       ),
    .wr_data        (wr_data      ),
    .rd_enb         (rd_enb       ),
    .rd_data        (rd_data      ),
    .full           (full         ),
    .empty          (empty        )
);

initial begin
    $dumpfile("async_fifo_dump.vcd");
    $dumpvars(0, tb_async_fifo);
    wr_clk = 1'b0;
    rd_clk = 1'b0; 
    start_rd = 1'b0; 
    rst_n = 1'b0;
    wr_enb = 1'b0;
    rd_enb = 1'b0;
    wr_data = {FIFO_WIDTH{1'd0}};
    #10 rst_n = 1'b1;
    #50 start_rd = 1'b1;
    #100000 $finish;
end

always #5 wr_clk = ~wr_clk;
always #10 rd_clk = ~rd_clk;

always @(posedge wr_clk or negedge rst_n) begin
    if(!rst_n) begin
        wr_enb <= 1'd0;
        wr_data <= {FIFO_WIDTH{1'd0}};
    end else begin
        if(wr_data == 8'd255) begin
            wr_enb <= 1'd0;
        end else if(!full) begin
            wr_enb <= 1'd1;
            wr_data <= wr_data + {{(FIFO_WIDTH-1){1'd0}},{1'd1}};
        end
    end
end

always@(posedge rd_clk or negedge rst_n) begin
    if(!rst_n) begin
        rd_enb <= 1'd0;
    end else begin
        rd_enb <= start_rd & !empty;
    end
end
endmodule

async_fifo_dump.vcd
$date
	Sun May 10 22:43:08 2026
$end
$version
	Icarus Verilog
$end
$timescale
	1ps
$end
$scope module tb_async_fifo $end
$var wire 8 ! rd_data [7:0] $end
$var wire 1 " full $end
$var wire 1 # empty $end
$var reg 1 $ rd_clk $end
$var reg 1 % rd_enb $end
$var reg 1 & rst_n $end
$var reg 1 ' start_rd $end
$var reg 1 ( wr_clk $end
$var reg 8 ) wr_data [7:0] $end
$var reg 1 * wr_enb $end
$scope module fifo $end
$var wire 1 $ rd_clk $end
$var wire 1 % rd_enb $end
$var wire 1 & rst_n $end
$var wire 1 ( wr_clk $end
$var wire 8 + wr_data [7:0] $end
$var wire 1 * wr_enb $end
$var wire 9 , sync_wr_addr [8:0] $end
$var wire 9 - sync_rd_addr [8:0] $end
$var wire 9 . nxt_wr_addr [8:0] $end
$var wire 9 / nxt_rd_addr [8:0] $end
$var wire 9 0 g_wr_addr [8:0] $end
$var wire 9 1 g_rd_addr [8:0] $end
$var wire 1 " full $end
$var wire 1 # empty $end
$var parameter 33 2 ADDR_WIDTH $end
$var parameter 40 3 FIFO_DEPTH $end
$var reg 9 4 rd_addr [8:0] $end
$var reg 8 5 rd_data [7:0] $end
$var reg 9 6 wr_addr [8:0] $end
$scope module conv1 $end
$var wire 9 7 in [8:0] $end
$var wire 9 8 out [8:0] $end
$var parameter 33 9 ADDR_WIDTH $end
$upscope $end
$scope module conv2 $end
$var wire 9 : in [8:0] $end
$var wire 9 ; out [8:0] $end
$var parameter 33 < ADDR_WIDTH $end
$upscope $end
$scope module sync1 $end
$var wire 1 ( clk $end
$var wire 9 = in [8:0] $end
$var wire 1 & rst_n $end
$var parameter 33 > ADDR_WIDTH $end
$var reg 9 ? in_d1 [8:0] $end
$var reg 9 @ in_d2 [8:0] $end
$var reg 9 A out [8:0] $end
$upscope $end
$scope module sync2 $end
$var wire 1 $ clk $end
$var wire 9 B in [8:0] $end
$var wire 1 & rst_n $end
$var parameter 33 C ADDR_WIDTH $end
$var reg 9 D in_d1 [8:0] $end
$var reg 9 E in_d2 [8:0] $end
$var reg 9 F out [8:0] $end
$upscope $end
$upscope $end
$upscope $end
$enddefinitions $end
$comment Show the parameter values. $end
$dumpall
b1001 C
b1001 >
b1001 <
b1001 9
b100000000 3
b1001 2
$end
#0
$dumpvars
b0 F
b0 E
b0 D
b1 B
b0 A
b0 @
b0 ?
b1 =
b1 ;
b1 :
b1 8
b1 7
b0 6
b0 5
b0 4
b1 1
b1 0
b1 /
b1 .
b0 -
b0 ,
b0 +
0*
b0 )
0(
0'
0&
0%
0$
0#
0"
b0 !
$end
#5000
1(
#10000
b1 D
0(
1$
1&
#15000
b1 ?
b1 )
b1 +
1*
1(
#20000
0(
0$
#25000
b11 B
b11 0
b11 8
b10 )
b10 +
b10 7
b10 .
b1 6
b1 @
1(
#30000
b1 E
b11 D
0(
1$
#35000
b10 B
b10 0
b1 -
b10 8
b1 A
b11 7
b11 .
b10 6
b11 )
b11 +
1(
#40000
0(
0$
#45000
b110 B
b110 0
b110 8
b100 )
b100 +
b100 7
b100 .
b11 6
1(
#50000
1#
b1 ,
b1 F
b11 E
b110 D
0(
1$
#55000
b111 B
b111 0
b111 8
b101 7
b101 .
b100 6
b101 )
b101 +
1(
#60000
0(
0$
1'
#65000
b101 B
b101 0
b101 8
b110 )
b110 +
b110 7
b110 .
b101 6
1(
#70000
0#
b11 ,
b11 F
b110 E
b101 D
0(
1$
#75000
b100 B
b100 0
b100 8
b111 7
b111 .
b110 6
b111 )
b111 +
1(
#80000
0(
0$
#85000
b1100 B
b1100 0
b1100 8
b1000 )
b1000 +
b1000 7
b1000 .
b111 6
1(
#90000
b110 ,
1%
b110 F
b101 E
b1100 D
0(
1$
#95000
b1101 B
b1101 0
b1101 8
b1001 7
b1001 .
b1000 6
b1001 )
b1001 +
1(
#100000
0(
0$
#105000
b1111 B
b1111 0
b1111 8
b1010 )
b1010 +
b1010 7
b1010 .
b1001 6
1(
#110000
b11 =
b11 1
b101 ,
b11 ;
b101 F
b1100 E
b1111 D
b10 :
b10 /
b1 4
b1 !
b1 5
0(
1$
#115000
b1110 B
b1110 0
b1110 8
b11 ?
b1011 7
b1011 .
b1010 6
b1011 )
b1011 +
1(
#120000
0(
0$
#125000
b1010 B
b1010 0
b1010 8
b1100 )
b1100 +
b1100 7
b1100 .
b1011 6
b11 @
1(
#130000
b10 =
b10 1
b10 ;
b1100 ,
b11 :
b11 /
b10 4
b10 !
b10 5
b1100 F
b1111 E
b1010 D
0(
1$
#135000
b1011 B
b1011 0
b11 -
b1011 8
b11 A
b10 ?
b1101 7
b1101 .
b1100 6
b1101 )
b1101 +
1(
#140000
0(
0$
#145000
b1001 B
b1001 0
b1001 8
b1110 )
b1110 +
b1110 7
b1110 .
b1101 6
b10 @
1(
#150000
b110 =
b110 1
b1111 ,
b110 ;
b1111 F
b1010 E
b1001 D
b100 :
b100 /
b11 4
b11 !
b11 5
0(
1$
#155000
b1000 B
b1000 0
b10 -
b1000 8
b10 A
b110 ?
b1111 7
b1111 .
b1110 6
b1111 )
b1111 +
1(
#160000
0(
0$
#165000
b11000 B
b11000 0
b11000 8
b10000 )
b10000 +
b10000 7
b10000 .
b1111 6
b110 @
1(
#170000
b111 =
b111 1
b111 ;
b1010 ,
b101 :
b101 /
b100 4
b100 !
b100 5
b1010 F
b1001 E
b11000 D
0(
1$
#175000
b11001 B
b11001 0
b110 -
b11001 8
b110 A
b111 ?
b10001 7
b10001 .
b10000 6
b10001 )
b10001 +
1(
#180000
0(
0$
#185000
b11011 B
b11011 0
b11011 8
b10010 )
b10010 +
b10010 7
b10010 .
b10001 6
b111 @
1(
#190000
b101 =
b101 1
b1001 ,
b101 ;
b1001 F
b11000 E
b11011 D
b110 :
b110 /
b101 4
b101 !
b101 5
0(
1$
#195000
b11010 B
b11010 0
b111 -
b11010 8
b111 A
b101 ?
b10011 7
b10011 .
b10010 6
b10011 )
b10011 +
1(
#200000
0(
0$
#205000
b11110 B
b11110 0
b11110 8
b10100 )
b10100 +
b10100 7
b10100 .
b10011 6
b101 @
1(
#210000
b100 =
b100 1
b100 ;
b11000 ,
b111 :
b111 /
b110 4
b110 !
b110 5
b11000 F
b11011 E
b11110 D
0(
1$
#215000
b11111 B
b11111 0
b101 -
b11111 8
b101 A
b100 ?
b10101 7
b10101 .
b10100 6
b10101 )
b10101 +
1(
#220000
0(
0$
#225000
b11101 B
b11101 0
b11101 8
b10110 )
b10110 +
b10110 7
b10110 .
b10101 6
b100 @
1(
#230000
b1100 =
b1100 1
b11011 ,
b1100 ;
b11011 F
b11110 E
b11101 D
b1000 :
b1000 /
b111 4
b111 !
b111 5
0(
1$
#235000
b11100 B
b11100 0
b100 -
b11100 8
b100 A
b1100 ?
b10111 7
b10111 .
b10110 6
b10111 )
b10111 +
1(
#240000
0(
0$
#245000
b10100 B
b10100 0
b10100 8
b11000 )
b11000 +
b11000 7
b11000 .
b10111 6
b1100 @
1(
#250000
b1101 =
b1101 1
b1101 ;
b11110 ,
b1001 :
b1001 /
b1000 4
b1000 !
b1000 5
b11110 F
b11101 E
b10100 D
0(
1$
#255000
b10101 B
b10101 0
b1100 -
b10101 8
b1100 A
b1101 ?
b11001 7
b11001 .
b11000 6
b11001 )
b11001 +
1(
#260000
0(
0$
#265000
b10111 B
b10111 0
b10111 8
b11010 )
b11010 +
b11010 7
b11010 .
b11001 6
b1101 @
1(
#270000
b1111 =
b1111 1
b11101 ,
b1111 ;
b11101 F
b10100 E
b10111 D
b1010 :
b1010 /
b1001 4
b1001 !
b1001 5
0(
1$
#275000
b10110 B
b10110 0
b1101 -
b10110 8
b1101 A
b1111 ?
b11011 7
b11011 .
b11010 6
b11011 )
b11011 +
1(
#280000
0(
0$
#285000
b10010 B
b10010 0
b10010 8
b11100 )
b11100 +
b11100 7
b11100 .
b11011 6
b1111 @
1(
#290000
b1110 =
b1110 1
b1110 ;
b10100 ,
b1011 :
b1011 /
b1010 4
b1010 !
b1010 5
b10100 F
b10111 E
b10010 D
0(
1$
#295000
b10011 B
b10011 0
b1111 -
b10011 8
b1111 A
b1110 ?
b11101 7
b11101 .
b11100 6
b11101 )
b11101 +
1(
#300000
0(
0$
#305000
b10001 B
b10001 0
b10001 8
b11110 )
b11110 +
b11110 7
b11110 .
b11101 6
b1110 @
1(
#310000
b1010 =
b1010 1
b10111 ,
b1010 ;
b10111 F
b10010 E
b10001 D
b1100 :
b1100 /
b1011 4
b1011 !
b1011 5
0(
1$
#315000
b10000 B
b10000 0
b1110 -
b10000 8
b1110 A
b1010 ?
b11111 7
b11111 .
b11110 6
b11111 )
b11111 +
1(
#320000
0(
0$
#325000
b110000 B
b110000 0
b110000 8
b100000 )
b100000 +
b100000 7
b100000 .
b11111 6
b1010 @
1(
#330000
b1011 =
b1011 1
b1011 ;
b10010 ,
b1101 :
b1101 /
b1100 4
b1100 !
b1100 5
b10010 F
b10001 E
b110000 D
0(
1$
#335000
b110001 B
b110001 0
b1010 -
b110001 8
b1010 A
b1011 ?
b100001 7
b100001 .
b100000 6
b100001 )
b100001 +
1(
#340000
0(
0$
#345000
b110011 B
b110011 0
b110011 8
b100010 )
b100010 +
b100010 7
b100010 .
b100001 6
b1011 @
1(
#350000
b1001 =
b1001 1
b10001 ,
b1001 ;
b10001 F
b110000 E
b110011 D
b1110 :
b1110 /
b1101 4
b1101 !
b1101 5
0(
1$
#355000
b110010 B
b110010 0
b1011 -
b110010 8
b1011 A
b1001 ?
b100011 7
b100011 .
b100010 6
b100011 )
b100011 +
1(
#360000
0(
0$
#365000
b110110 B
b110110 0
b110110 8
b100100 )
b100100 +
b100100 7
b100100 .
b100011 6
b1001 @
1(
#370000
b1000 =
b1000 1
b1000 ;
b110000 ,
b1111 :
b1111 /
b1110 4
b1110 !
b1110 5
b110000 F
b110011 E
b110110 D
0(
1$
#375000
b110111 B
b110111 0
b1001 -
b110111 8
b1001 A
b1000 ?
b100101 7
b100101 .
b100100 6
b100101 )
b100101 +
1(
#380000
0(
0$
#385000
b110101 B
b110101 0
b110101 8
b100110 )
b100110 +
b100110 7
b100110 .
b100101 6
b1000 @
1(
#390000
b11000 =
b11000 1
b110011 ,
b11000 ;
b110011 F
b110110 E
b110101 D
b10000 :
b10000 /
b1111 4
b1111 !
b1111 5
0(
1$
#395000
b110100 B
b110100 0
b1000 -
b110100 8
b1000 A
b11000 ?
b100111 7
b100111 .
b100110 6
b100111 )
b100111 +
1(
#400000
0(
0$
#405000
b111100 B
b111100 0
b111100 8
b101000 )
b101000 +
b101000 7
b101000 .
b100111 6
b11000 @
1(
#410000
b11001 =
b11001 1
b11001 ;
b110110 ,
b10001 :
b10001 /
b10000 4
b10000 !
b10000 5
b110110 F
b110101 E
b111100 D
0(
1$
#415000
b111101 B
b111101 0
b11000 -
b111101 8
b11000 A
b11001 ?
b101001 7
b101001 .
b101000 6
b101001 )
b101001 +
1(
#420000
0(
0$
#425000
b111111 B
b111111 0
b111111 8
b101010 )
b101010 +
b101010 7
b101010 .
b101001 6
b11001 @
1(
#430000
b11011 =
b11011 1
b110101 ,
b11011 ;
b110101 F
b111100 E
b111111 D
b10010 :
b10010 /
b10001 4
b10001 !
b10001 5
0(
1$
#435000
b111110 B
b111110 0
b11001 -
b111110 8
b11001 A
b11011 ?
b101011 7
b101011 .
b101010 6
b101011 )
b101011 +
1(
#440000
0(
0$
#445000
b111010 B
b111010 0
b111010 8
b101100 )
b101100 +
b101100 7
b101100 .
b101011 6
b11011 @
1(
#450000
b11010 =
b11010 1
b11010 ;
b111100 ,
b10011 :
b10011 /
b10010 4
b10010 !
b10010 5
b111100 F
b111111 E
b111010 D
0(
1$
#455000
b111011 B
b111011 0
b11011 -
b111011 8
b11011 A
b11010 ?
b101101 7
b101101 .
b101100 6
b101101 )
b101101 +
1(
#460000
0(
0$
#465000
b111001 B
b111001 0
b111001 8
b101110 )
b101110 +
b101110 7
b101110 .
b101101 6
b11010 @
1(
#470000
b11110 =
b11110 1
b111111 ,
b11110 ;
b111111 F
b111010 E
b111001 D
b10100 :
b10100 /
b10011 4
b10011 !
b10011 5
0(
1$
#475000
b111000 B
b111000 0
b11010 -
b111000 8
b11010 A
b11110 ?
b101111 7
b101111 .
b101110 6
b101111 )
b101111 +
1(
#480000
0(
0$
#485000
b101000 B
b101000 0
b101000 8
b110000 )
b110000 +
b110000 7
b110000 .
b101111 6
b11110 @
1(
#490000
b11111 =
b11111 1
b11111 ;
b111010 ,
b10101 :
b10101 /
b10100 4
b10100 !
b10100 5
b111010 F
b111001 E
b101000 D
0(
1$
#495000
b101001 B
b101001 0
b11110 -
b101001 8
b11110 A
b11111 ?
b110001 7
b110001 .
b110000 6
b110001 )
b110001 +
1(
#500000
0(
0$
#505000
b101011 B
b101011 0
b101011 8
b110010 )
b110010 +
b110010 7
b110010 .
b110001 6
b11111 @
1(
#510000
b11101 =
b11101 1
b111001 ,
b11101 ;
b111001 F
b101000 E
b101011 D
b10110 :
b10110 /
b10101 4
b10101 !
b10101 5
0(
1$
#515000
b101010 B
b101010 0
b11111 -
b101010 8
b11111 A
b11101 ?
b110011 7
b110011 .
b110010 6
b110011 )
b110011 +
1(
#520000
0(
0$
#525000
b101110 B
b101110 0
b101110 8
b110100 )
b110100 +
b110100 7
b110100 .
b110011 6
b11101 @
1(
#530000
b11100 =
b11100 1
b11100 ;
b101000 ,
b10111 :
b10111 /
b10110 4
b10110 !
b10110 5
b101000 F
b101011 E
b101110 D
0(
1$
#535000
b101111 B
b101111 0
b11101 -
b101111 8
b11101 A
b11100 ?
b110101 7
b110101 .
b110100 6
b110101 )
b110101 +
1(
#540000
0(
0$
#545000
b101101 B
b101101 0
b101101 8
b110110 )
b110110 +
b110110 7
b110110 .
b110101 6
b11100 @
1(
#550000
b10100 =
b10100 1
b101011 ,
b10100 ;
b101011 F
b101110 E
b101101 D
b11000 :
b11000 /
b10111 4
b10111 !
b10111 5
0(
1$
#555000
b101100 B
b101100 0
b11100 -
b101100 8
b11100 A
b10100 ?
b110111 7
b110111 .
b110110 6
b110111 )
b110111 +
1(
#560000
0(
0$
#565000
b100100 B
b100100 0
b100100 8
b111000 )
b111000 +
b111000 7
b111000 .
b110111 6
b10100 @
1(
#570000
b10101 =
b10101 1
b10101 ;
b101110 ,
b11001 :
b11001 /
b11000 4
b11000 !
b11000 5
b101110 F
b101101 E
b100100 D
0(
1$
#575000
b100101 B
b100101 0
b10100 -
b100101 8
b10100 A
b10101 ?
b111001 7
b111001 .
b111000 6
b111001 )
b111001 +
1(
#580000
0(
0$
#585000
b100111 B
b100111 0
b100111 8
b111010 )
b111010 +
b111010 7
b111010 .
b111001 6
b10101 @
1(
#590000
b10111 =
b10111 1
b101101 ,
b10111 ;
b101101 F
b100100 E
b100111 D
b11010 :
b11010 /
b11001 4
b11001 !
b11001 5
0(
1$
#595000
b100110 B
b100110 0
b10101 -
b100110 8
b10101 A
b10111 ?
b111011 7
b111011 .
b111010 6
b111011 )
b111011 +
1(
#600000
0(
0$
#605000
b100010 B
b100010 0
b100010 8
b111100 )
b111100 +
b111100 7
b111100 .
b111011 6
b10111 @
1(
#610000
b10110 =
b10110 1
b10110 ;
b100100 ,
b11011 :
b11011 /
b11010 4
b11010 !
b11010 5
b100100 F
b100111 E
b100010 D
0(
1$
#615000
b100011 B
b100011 0
b10111 -
b100011 8
b10111 A
b10110 ?
b111101 7
b111101 .
b111100 6
b111101 )
b111101 +
1(
#620000
0(
0$
#625000
b100001 B
b100001 0
b100001 8
b111110 )
b111110 +
b111110 7
b111110 .
b111101 6
b10110 @
1(
#630000
b10010 =
b10010 1
b100111 ,
b10010 ;
b100111 F
b100010 E
b100001 D
b11100 :
b11100 /
b11011 4
b11011 !
b11011 5
0(
1$
#635000
b100000 B
b100000 0
b10110 -
b100000 8
b10110 A
b10010 ?
b111111 7
b111111 .
b111110 6
b111111 )
b111111 +
1(
#640000
0(
0$
#645000
b1100000 B
b1100000 0
b1100000 8
b1000000 )
b1000000 +
b1000000 7
b1000000 .
b111111 6
b10010 @
1(
#650000
b10011 =
b10011 1
b10011 ;
b100010 ,
b11101 :
b11101 /
b11100 4
b11100 !
b11100 5
b100010 F
b100001 E
b1100000 D
0(
1$
#655000
b1100001 B
b1100001 0
b10010 -
b1100001 8
b10010 A
b10011 ?
b1000001 7
b1000001 .
b1000000 6
b1000001 )
b1000001 +
1(
#660000
0(
0$
#665000
b1100011 B
b1100011 0
b1100011 8
b1000010 )
b1000010 +
b1000010 7
b1000010 .
b1000001 6
b10011 @
1(
#670000
b10001 =
b10001 1
b100001 ,
b10001 ;
b100001 F
b1100000 E
b1100011 D
b11110 :
b11110 /
b11101 4
b11101 !
b11101 5
0(
1$
#675000
b1100010 B
b1100010 0
b10011 -
b1100010 8
b10011 A
b10001 ?
b1000011 7
b1000011 .
b1000010 6
b1000011 )
b1000011 +
1(
#680000
0(
0$
#685000
b1100110 B
b1100110 0
b1100110 8
b1000100 )
b1000100 +
b1000100 7
b1000100 .
b1000011 6
b10001 @
1(
#690000
b10000 =
b10000 1
b10000 ;
b1100000 ,
b11111 :
b11111 /
b11110 4
b11110 !
b11110 5
b1100000 F
b1100011 E
b1100110 D
0(
1$
#695000
b1100111 B
b1100111 0
b10001 -
b1100111 8
b10001 A
b10000 ?
b1000101 7
b1000101 .
b1000100 6
b1000101 )
b1000101 +
1(
#700000
0(
0$
#705000
b1100101 B
b1100101 0
b1100101 8
b1000110 )
b1000110 +
b1000110 7
b1000110 .
b1000101 6
b10000 @
1(
#710000
b110000 =
b110000 1
b1100011 ,
b110000 ;
b1100011 F
b1100110 E
b1100101 D
b100000 :
b100000 /
b11111 4
b11111 !
b11111 5
0(
1$
#715000
b1100100 B
b1100100 0
b10000 -
b1100100 8
b10000 A
b110000 ?
b1000111 7
b1000111 .
b1000110 6
b1000111 )
b1000111 +
1(
#720000
0(
0$
#725000
b1101100 B
b1101100 0
b1101100 8
b1001000 )
b1001000 +
b1001000 7
b1001000 .
b1000111 6
b110000 @
1(
#730000
b110001 =
b110001 1
b110001 ;
b1100110 ,
b100001 :
b100001 /
b100000 4
b100000 !
b100000 5
b1100110 F
b1100101 E
b1101100 D
0(
1$
#735000
b1101101 B
b1101101 0
b110000 -
b1101101 8
b110000 A
b110001 ?
b1001001 7
b1001001 .
b1001000 6
b1001001 )
b1001001 +
1(
#740000
0(
0$
#745000
b1101111 B
b1101111 0
b1101111 8
b1001010 )
b1001010 +
b1001010 7
b1001010 .
b1001001 6
b110001 @
1(
#750000
b110011 =
b110011 1
b1100101 ,
b110011 ;
b1100101 F
b1101100 E
b1101111 D
b100010 :
b100010 /
b100001 4
b100001 !
b100001 5
0(
1$
#755000
b1101110 B
b1101110 0
b110001 -
b1101110 8
b110001 A
b110011 ?
b1001011 7
b1001011 .
b1001010 6
b1001011 )
b1001011 +
1(
#760000
0(
0$
#765000
b1101010 B
b1101010 0
b1101010 8
b1001100 )
b1001100 +
b1001100 7
b1001100 .
b1001011 6
b110011 @
1(
#770000
b110010 =
b110010 1
b110010 ;
b1101100 ,
b100011 :
b100011 /
b100010 4
b100010 !
b100010 5
b1101100 F
b1101111 E
b1101010 D
0(
1$
#775000
b1101011 B
b1101011 0
b110011 -
b1101011 8
b110011 A
b110010 ?
b1001101 7
b1001101 .
b1001100 6
b1001101 )
b1001101 +
1(
#780000
0(
0$
#785000
b1101001 B
b1101001 0
b1101001 8
b1001110 )
b1001110 +
b1001110 7
b1001110 .
b1001101 6
b110010 @
1(
#790000
b110110 =
b110110 1
b1101111 ,
b110110 ;
b1101111 F
b1101010 E
b1101001 D
b100100 :
b100100 /
b100011 4
b100011 !
b100011 5
0(
1$
#795000
b1101000 B
b1101000 0
b110010 -
b1101000 8
b110010 A
b110110 ?
b1001111 7
b1001111 .
b1001110 6
b1001111 )
b1001111 +
1(
#800000
0(
0$
#805000
b1111000 B
b1111000 0
b1111000 8
b1010000 )
b1010000 +
b1010000 7
b1010000 .
b1001111 6
b110110 @
1(
#810000
b110111 =
b110111 1
b110111 ;
b1101010 ,
b100101 :
b100101 /
b100100 4
b100100 !
b100100 5
b1101010 F
b1101001 E
b1111000 D
0(
1$
#815000
b1111001 B
b1111001 0
b110110 -
b1111001 8
b110110 A
b110111 ?
b1010001 7
b1010001 .
b1010000 6
b1010001 )
b1010001 +
1(
#820000
0(
0$
#825000
b1111011 B
b1111011 0
b1111011 8
b1010010 )
b1010010 +
b1010010 7
b1010010 .
b1010001 6
b110111 @
1(
#830000
b110101 =
b110101 1
b1101001 ,
b110101 ;
b1101001 F
b1111000 E
b1111011 D
b100110 :
b100110 /
b100101 4
b100101 !
b100101 5
0(
1$
#835000
b1111010 B
b1111010 0
b110111 -
b1111010 8
b110111 A
b110101 ?
b1010011 7
b1010011 .
b1010010 6
b1010011 )
b1010011 +
1(
#840000
0(
0$
#845000
b1111110 B
b1111110 0
b1111110 8
b1010100 )
b1010100 +
b1010100 7
b1010100 .
b1010011 6
b110101 @
1(
#850000
b110100 =
b110100 1
b110100 ;
b1111000 ,
b100111 :
b100111 /
b100110 4
b100110 !
b100110 5
b1111000 F
b1111011 E
b1111110 D
0(
1$
#855000
b1111111 B
b1111111 0
b110101 -
b1111111 8
b110101 A
b110100 ?
b1010101 7
b1010101 .
b1010100 6
b1010101 )
b1010101 +
1(
#860000
0(
0$
#865000
b1111101 B
b1111101 0
b1111101 8
b1010110 )
b1010110 +
b1010110 7
b1010110 .
b1010101 6
b110100 @
1(
#870000
b111100 =
b111100 1
b1111011 ,
b111100 ;
b1111011 F
b1111110 E
b1111101 D
b101000 :
b101000 /
b100111 4
b100111 !
b100111 5
0(
1$
#875000
b1111100 B
b1111100 0
b110100 -
b1111100 8
b110100 A
b111100 ?
b1010111 7
b1010111 .
b1010110 6
b1010111 )
b1010111 +
1(
#880000
0(
0$
#885000
b1110100 B
b1110100 0
b1110100 8
b1011000 )
b1011000 +
b1011000 7
b1011000 .
b1010111 6
b111100 @
1(
#890000
b111101 =
b111101 1
b111101 ;
b1111110 ,
b101001 :
b101001 /
b101000 4
b101000 !
b101000 5
b1111110 F
b1111101 E
b1110100 D
0(
1$
#895000
b1110101 B
b1110101 0
b111100 -
b1110101 8
b111100 A
b111101 ?
b1011001 7
b1011001 .
b1011000 6
b1011001 )
b1011001 +
1(
#900000
0(
0$
#905000
b1110111 B
b1110111 0
b1110111 8
b1011010 )
b1011010 +
b1011010 7
b1011010 .
b1011001 6
b111101 @
1(
#910000
b111111 =
b111111 1
b1111101 ,
b111111 ;
b1111101 F
b1110100 E
b1110111 D
b101010 :
b101010 /
b101001 4
b101001 !
b101001 5
0(
1$
#915000
b1110110 B
b1110110 0
b111101 -
b1110110 8
b111101 A
b111111 ?
b1011011 7
b1011011 .
b1011010 6
b1011011 )
b1011011 +
1(
#920000
0(
0$
#925000
b1110010 B
b1110010 0
b1110010 8
b1011100 )
b1011100 +
b1011100 7
b1011100 .
b1011011 6
b111111 @
1(
#930000
b111110 =
b111110 1
b111110 ;
b1110100 ,
b101011 :
b101011 /
b101010 4
b101010 !
b101010 5
b1110100 F
b1110111 E
b1110010 D
0(
1$
#935000
b1110011 B
b1110011 0
b111111 -
b1110011 8
b111111 A
b111110 ?
b1011101 7
b1011101 .
b1011100 6
b1011101 )
b1011101 +
1(
#940000
0(
0$
#945000
b1110001 B
b1110001 0
b1110001 8
b1011110 )
b1011110 +
b1011110 7
b1011110 .
b1011101 6
b111110 @
1(
#950000
b111010 =
b111010 1
b1110111 ,
b111010 ;
b1110111 F
b1110010 E
b1110001 D
b101100 :
b101100 /
b101011 4
b101011 !
b101011 5
0(
1$
#955000
b1110000 B
b1110000 0
b111110 -
b1110000 8
b111110 A
b111010 ?
b1011111 7
b1011111 .
b1011110 6
b1011111 )
b1011111 +
1(
#960000
0(
0$
#965000
b1010000 B
b1010000 0
b1010000 8
b1100000 )
b1100000 +
b1100000 7
b1100000 .
b1011111 6
b111010 @
1(
#970000
b111011 =
b111011 1
b111011 ;
b1110010 ,
b101101 :
b101101 /
b101100 4
b101100 !
b101100 5
b1110010 F
b1110001 E
b1010000 D
0(
1$
#975000
b1010001 B
b1010001 0
b111010 -
b1010001 8
b111010 A
b111011 ?
b1100001 7
b1100001 .
b1100000 6
b1100001 )
b1100001 +
1(
#980000
0(
0$
#985000
b1010011 B
b1010011 0
b1010011 8
b1100010 )
b1100010 +
b1100010 7
b1100010 .
b1100001 6
b111011 @
1(
#990000
b111001 =
b111001 1
b1110001 ,
b111001 ;
b1110001 F
b1010000 E
b1010011 D
b101110 :
b101110 /
b101101 4
b101101 !
b101101 5
0(
1$
